{"dependencies":null,"dependency":{"module1":{"config_path":"/projects/gruntwork/terragrunt-tests/json-formatting/app/../module1","mock_outputs":{"outlist":["subnet-1","subnet-2","subnet-3"]},"mock_outputs_allowed_terraform_commands":["validate","plan"],"mock_outputs_merge_strategy_with_state":null,"mock_outputs_merge_with_state":null,"name":"module1","outputs":null,"skip":null}},"download_dir":"","generate":{},"iam_assume_role_duration":null,"iam_assume_role_session_name":"","iam_role":"","inputs":{"in_list":["abc","123","000"]},"locals":null,"retry_max_attempts":null,"retry_sleep_interval_sec":null,"retryable_errors":null,"skip":false,"terraform_binary":"","terraform_version_constraint":"","terragrunt_version_constraint":""}